<?xml version="1.0" encoding="utf-8" ?><dwsync><file name="add.ctp" server="blabfeed.com" local="3448729680" remote="16333631568" /><file name="edit.ctp" server="blabfeed.com" local="3448729680" remote="16333631568" /><file name="feed.ctp" server="blabfeed.com" local="3448729680" remote="16333631568" /><file name="index.ctp" server="blabfeed.com" local="3448729680" remote="16333631568" /><file name="view.ctp" server="blabfeed.com" local="3448729680" remote="16333631568" /><file name="client_add.ctp" server="blabfeed.com" local="3448729680" remote="16333631568" /><file name="client_edit.ctp" server="blabfeed.com" local="3448729680" remote="16333631568" /><file name="client_feed.ctp" server="blabfeed.com" local="3448729680" remote="16333631568" /><file name="client_index.ctp" server="blabfeed.com" local="3448729680" remote="16333631568" /><file name="client_view.ctp" server="blabfeed.com" local="3448729680" remote="16333631568" /><file name="update.ctp" server="blabfeed.com" local="3448729680" remote="16333631568" /></dwsync>